Banz_domainfile_generator/.gitignore
Banz_domainfile_generator/__init__.py
Banz_domainfile_generator/domainfile_generator.py
Banz_domainfile_generator/enum_field.py
Banz_domainfile_generator/field.py
Banz_domainfile_generator/object.py
Banz_domainfile_generator/reference.py
Banz_domainfile_generator/templates/templateBase.py
Banz_domainfile_generator/templates/templateBo.py
Banz_domainfile_generator/templates/templateBto.py
Banz_domainfile_generator/templates/templateDto.py
Banz_domainfile_generator/templates/templateEnum.py
Banz_domainfile_generator/templates/templateLiquibase.py
Banz_domainfile_generator/templates/templateLogic.py
Banz_domainfile_generator/templates/templateResource.py
Banz_domainfile_generator/templates/templateService.py
Banz_domainfile_generator/templates/templateValidator.py
Banz_domainfile_generator/test.py
Banz_domainfile_generator/test/backend/domain/src/main/java/org/derbanz/cluborga/domain/base/AbstractBusinessObject.java
Banz_domainfile_generator/test/backend/domain/src/main/java/org/derbanz/cluborga/domain/base/I18N.java
Banz_domainfile_generator/test/backend/domain/src/main/java/org/derbanz/cluborga/domain/base/dto/BaseDto.java
Banz_domainfile_generator/test/backend/domain/src/main/java/org/derbanz/cluborga/domain/base/exception/ObjectNotFoundException.java
Banz_domainfile_generator/test/backend/domain/src/main/java/org/derbanz/cluborga/domain/base/transfer/BaseBto.java
Banz_domainfile_generator/test/backend/domain/src/main/java/org/derbanz/cluborga/domain/base/transfer/BaseBtoMapper.java
Banz_domainfile_generator/test/backend/domain/src/main/java/org/derbanz/cluborga/domain/base/util/BaseDtoMapper.java
Banz_domainfile_generator/test/backend/domain/src/main/java/org/derbanz/cluborga/domain/enums/ContactType.java
Banz_domainfile_generator/test/backend/domain/src/main/java/org/derbanz/cluborga/domain/enums/Gender.java
Banz_domainfile_generator/test/backend/domain/src/main/java/org/derbanz/cluborga/domain/enums/MembershipStatus.java
banz_domainfile_generator-1.1.0.dist-info/METADATA
banz_domainfile_generator-1.1.0.dist-info/WHEEL
banz_domainfile_generator-1.1.0.dist-info/entry_points.txt
banz_domainfile_generator-1.1.0.dist-info/licenses/LICENSE
banz_domainfile_generator-1.1.0.dist-info/RECORD
